wikikoro/__init__.py
wikikoro/wiki.py
wikikoro-0.1.dist-info/LICENSE
wikikoro-0.1.dist-info/METADATA
wikikoro-0.1.dist-info/WHEEL
wikikoro-0.1.dist-info/top_level.txt
wikikoro-0.1.dist-info/RECORD
