Metadata-Version: 2.1
Name: wikikoro
Version: 0.1
Summary: Find In wikipedia
Home-page: http://github.com/AshfakYeafi/wikiit
Author: Ashfak Yeafi
Author-email: yeafiashfak@gmail.com
License: MIT
Platform: UNKNOWN
Classifier: Programming Language :: Python :: 3
Classifier: License :: OSI Approved :: MIT License
Classifier: Operating System :: OS Independent
License-File: LICENSE
Requires-Dist: wikipedia
